[
    {
        "team": {
            "id": 45,
            "name": "Everton",
            "code": "EVE",
            "country": "England",
            "founded": 1878,
            "national": false,
            "logo": "https://media.api-sports.io/football/teams/45.png"
        },
        "venue": {
            "id": 8560,
            "name": "Goodison Park",
            "address": "Goodison Road",
            "city": "Liverpool",
            "capacity": 40569,
            "surface": "grass",
            "image": "https://media-3.api-sports.io/football/venues/8560.png"
        }
    }
]